quickdrop/__init__.py
quickdrop/cli.py
quickdrop_cli-0.1.4.dist-info/METADATA
quickdrop_cli-0.1.4.dist-info/WHEEL
quickdrop_cli-0.1.4.dist-info/entry_points.txt
quickdrop_cli-0.1.4.dist-info/top_level.txt
quickdrop_cli-0.1.4.dist-info/RECORD
